united_payment/__init__.py
united_payment/client.py
united_payment/constants.py
united_payment/exceptions.py
united_payment-0.1.1.dist-info/LICENSE
united_payment-0.1.1.dist-info/METADATA
united_payment-0.1.1.dist-info/WHEEL
united_payment-0.1.1.dist-info/RECORD
