Metadata-Version: 2.1
Name: united_payment
Version: 0.1.1
Summary: A Python package for easy integration with the UnitedPayment API, simplifying payment processing and transaction management. It offers a user-friendly interface, comprehensive documentation, and built-in tests, making integration effortless for developers.
License: MIT
Author: Nijat-Akhundzada
Author-email: nicataxundzada@gmail.com
Requires-Python: >=3.11,<4.0
Classifier: License :: OSI Approved :: MIT License
Classifier: Programming Language :: Python :: 3
Classifier: Programming Language :: Python :: 3.11
Classifier: Programming Language :: Python :: 3.12
Requires-Dist: requests (>=2.32.3,<3.0.0)
